{
  "title": "Λουκούμια",
  "slug": "loukoumia",
  "category": "syskevasmena",
  "intro": "Τα λουκούμια αποτελούν διαχρονικό ελληνικό κέρασμα, με απαλή υφή, γνώριμες γεύσεις και πρακτική παρουσία για κάθε σημείο πώλησης.\n\nΗ κατηγορία περιλαμβάνει κλασικές και πιο ιδιαίτερες επιλογές, κατάλληλες για λιανική, κεράσματα και επαγγελματικούς χώρους που αναζητούν προϊόντα με σταθερή ζήτηση.\n\nΜε εύκολη διάθεση και οικεία γευστική ταυτότητα, προσφέρουν μια αξιόπιστη λύση για καθημερινή εμπορική χρήση.",
  "banner_image": "/assets/branding/logo-slogan.png",
  "meta_description": "Λουκούμια με κλασικές και ιδιαίτερες γεύσεις για λιανική, κεράσματα και επαγγελματική διάθεση.",
  "order": 6,
  "is_visible": true
}
